qiskit_iceberg_transpiler/__init__.py
qiskit_iceberg_transpiler/gates.py
qiskit_iceberg_transpiler/transpiler.py
qiskit_iceberg_transpiler/util.py
qiskit_iceberg_transpiler-0.2.0.dist-info/LICENSE
qiskit_iceberg_transpiler-0.2.0.dist-info/METADATA
qiskit_iceberg_transpiler-0.2.0.dist-info/WHEEL
qiskit_iceberg_transpiler-0.2.0.dist-info/RECORD
