Metadata-Version: 2.1
Name: qiskit-iceberg-transpiler
Version: 0.2.0
Summary: Qiskit transpiler to convert logical circuits to physical circuits using the [[k+2, k, 2]] Iceberg code
License: Apache-2.0
Author: Jim Furches
Author-email: jfurches@gatech.edu
Requires-Python: >=3.12,<4.0
Classifier: License :: OSI Approved :: Apache Software License
Classifier: Programming Language :: Python :: 3
Classifier: Programming Language :: Python :: 3.12
Classifier: Programming Language :: Python :: 3.13
Requires-Dist: numpy (>=2.0.0,<3.0.0)
Requires-Dist: qiskit (>=1.2.0,<2.0.0)
